{
  "project_info": {
    "project_number": "907407832446",
    "project_id": "instagram-clone-fcdfb",
    "storage_bucket": "instagram-clone-fcdfb.appspot.com"
  },
  "client": [
    {
      "client_info": {
        "mobilesdk_app_id": "1:907407832446:android:a6d0ffcba65ad29e4baf2f",
        "android_client_info": {
          "package_name": "com.example.instagram_clone"
        }
      },
      "oauth_client": [],
      "api_key": [
        {
          "current_key": "AIzaSyBewb27ZIZTOR9AnTlALbciCY7K8_F3v2o"
        }
      ],
      "services": {
        "appinvite_service": {
          "other_platform_oauth_client": []
        }
      }
    }
  ],
  "configuration_version": "1"
}